MANIFEST.in
README.md
requirements.txt
setup.cfg
setup.py
pypair/__init__.py
pypair/association.py
pypair/biserial.py
pypair/contingency.py
pypair/continuous.py
pypair/decorator.py
pypair/spark.py
pypair/util.py
pypair.egg-info/PKG-INFO
pypair.egg-info/SOURCES.txt
pypair.egg-info/dependency_links.txt
pypair.egg-info/top_level.txt