Metadata-Version: 2.1
Name: pypair
Version: 3.0.9
Summary: Pairwise association measures of statistical variable types
Home-page: https://github.com/oneoffcoder/py-pair
Author: Jee Vang
Author-email: vangjee@gmail.com
License: UNKNOWN
Keywords: statistics,pairwise,association,correlation,concordance,measurement,strength,pyspark
Platform: UNKNOWN
Classifier: Programming Language :: Python :: 3
Classifier: License :: OSI Approved :: Apache Software License
Classifier: Operating System :: OS Independent
Classifier: Topic :: Scientific/Engineering :: Artificial Intelligence
Classifier: Intended Audience :: Developers
Classifier: Intended Audience :: Science/Research
Classifier: Development Status :: 5 - Production/Stable
